lost_spc/__init__.py
lost_spc/calculations/__init__.py
lost_spc/calculations/control_limits.py
lost_spc/calculations/spc_values.py
lost_spc/checks.py
lost_spc/constants/__init__.py
lost_spc/constants/_d_table.py
lost_spc/plots/__init__.py
lost_spc/plots/cards.py
lost_spc/plots/plots.py
lost_spc/utils.py
lost_spc-0.2.1.dist-info/LICENSE
lost_spc-0.2.1.dist-info/METADATA
lost_spc-0.2.1.dist-info/WHEEL
lost_spc-0.2.1.dist-info/RECORD
